ncs_pycli/__init__.py
ncs_pycli/ncs_pycli.py
ncs_pycli-1.3.4.dist-info/METADATA
ncs_pycli-1.3.4.dist-info/WHEEL
ncs_pycli-1.3.4.dist-info/entry_points.txt
ncs_pycli-1.3.4.dist-info/top_level.txt
ncs_pycli-1.3.4.dist-info/RECORD
