Metadata-Version: 2.1
Name: ncs-pycli
Version: 1.3.4
Summary: Gives you an interactive NSO python shell with tab completion.
Home-page: https://github.com/NSO-developer/ncs_pycli.git
Author: Hakan Niska, Kiran Kumar Kotari
Author-email: hniska@cisco.com, kkotari@cisco.com
License: UNKNOWN
Keywords: ncs-pycli ncs_pycli
Platform: UNKNOWN
Classifier: Development Status :: 3 - Alpha
Classifier: Intended Audience :: Developers
Classifier: Topic :: Software Development :: Build Tools
Classifier: License :: OSI Approved :: MIT License
Classifier: Operating System :: OS Independent
Classifier: Programming Language :: Python :: 2.7
Classifier: Programming Language :: Python :: 3.5
Classifier: Programming Language :: Python :: 3.6
Classifier: Programming Language :: Python :: 3.7
Requires-Dist: ipython
